<?xml version="1.0" encoding="UTF-8"?>
<!--This file was created by G+Smo 21.12.0-->
<xml>
 <Matrix rows="6" cols="8" id="0">0.125 35 0.6907683130684822 35.20471656422921 3322.846633107407 25.52266989193081 1.144919230213085e-313 236009.40856 
0.0625 135 0.0145670146190024 0.6386879213974546 58.60403022772528 0.343575651197738 0 472018.81712 
0.03125 527 0.0005610103916273634 0.03794503075913856 3.499833201165406 0.001587477522339222 4.689589165708543e-310 944037.63424 
0.015625 2079 2.007836285044933e-05 0.00296516832716016 0.6440251209178475 0.0001722526795888144 4.689589161888032e-310 1888075.26848 
0.0078125 8255 9.229356327857909e-07 0.0003373408479935281 0.1549978111132933 2.058589812760806e-05 4.243991584993752e-313 3776150.53696 
0.00390625 32895 9.361295016097118e-08 4.157433515998533e-05 0.03844634200968962 2.542444712388559e-06 5.246977158834038e-321 7552301.07392 
</Matrix>
 <string label="Label" id="1">Meshsize, dofs, l2err, h1err, h2err, iFaceErr, cond_num, (penalty)</string>
 <string label="Degree" id="2">3</string>
 <string label="Regularity" id="3">2</string>
 <string label="NumRefine" id="4">5</string>
 <string label="Method" id="5">3</string>
</xml>

