<?xml version="1.0" encoding="UTF-8"?>
<!--This file was created by G+Smo 21.12.0-->
<xml>
 <Matrix rows="6" cols="8" id="0">0.125 35 0.2236255502863668 9.160541373524049 1177.458414707683 25.85868968060706 1.140515051527157e-313 0.01808 
0.0625 135 0.01150913827933311 0.4728105276302822 50.41727092984104 0.344366775065902 0 0.03616 
0.03125 527 0.0002968800950274722 0.027389639022093 2.966372322638513 0.001718393958798665 4.671549649810979e-310 0.07232 
0.015625 2079 1.394846738457734e-05 0.002829162031762795 0.6402541620353197 0.00017377405952622 4.671549645990468e-310 0.14464 
0.0078125 8255 7.99603946283772e-07 0.0003357570991957311 0.1549500326817368 2.067646272904102e-05 4.243991584993752e-313 0.28928 
0.00390625 32895 4.86287453286208e-08 4.136943957426076e-05 0.03844362221323325 2.551768340170576e-06 5.246977158834038e-321 0.57856 
</Matrix>
 <string label="Label" id="1">Meshsize, dofs, l2err, h1err, h2err, iFaceErr, cond_num, (penalty)</string>
 <string label="Degree" id="2">3</string>
 <string label="Regularity" id="3">2</string>
 <string label="NumRefine" id="4">5</string>
 <string label="Method" id="5">3</string>
</xml>

