<?xml version="1.0" encoding="UTF-8"?>
<!--This file was created by G+Smo 21.12.0-->
<xml>
 <Matrix rows="6" cols="8" id="0">0.25 44 0.763787221906682 10.2912844802699 161.1762945699392 0.06572125977467812 1.141233712844524e-313 221596.52892 
0.125 152 0.1516661412315071 2.325942181839222 52.66361315235807 0.03021310229656828 0 443193.05784 
0.0625 560 0.03689791969487938 0.7981827065642733 18.9197352416382 0.01400804668031079 0 886386.11568 
0.03125 2144 0.0003311262031387038 0.008173523813813699 0.2934093675693897 0.001265179161991978 0 1772772.23136 
0.015625 8384 2.127592086696801e-06 6.857374536814199e-05 0.02237904281767898 6.400077106924713e-05 7.851384429634715e-313 3545544.46272 
0.0078125 33152 1.836883303976115e-05 0.0001188353316298502 0.00300066792725031 3.756604639040964e-06 4.674493287680738e-310 7091088.92544 
</Matrix>
 <string label="Label" id="1">Meshsize, dofs, l2err, h1err, h2err, iFaceErr, cond_num, (penalty)</string>
 <string label="Degree" id="2">4</string>
 <string label="Regularity" id="3">3</string>
 <string label="NumRefine" id="4">5</string>
 <string label="Method" id="5">3</string>
</xml>

