<?xml version="1.0" encoding="UTF-8"?>
<!--This file was created by G+Smo 21.12.0-->
<xml>
 <Matrix rows="6" cols="8" id="0">0.25 44 0.7256932023784817 9.86323171490554 155.6482966217308 0.1261408998134818 1.138244312479098e-313 17820.02972 
0.125 152 0.09391255736673759 1.919056026912903 47.13528046779472 0.05714275202626867 0 35640.05944 
0.0625 560 0.008901769113102434 0.2116414160665828 5.763162405424247 0.02937182613213319 0 71280.11887999999 
0.03125 2144 2.861502823649462e-05 0.001218840410948933 0.1976952146060598 0.001277855492842816 0 142560.23776 
0.015625 8384 2.079455161908562e-07 5.512793731887805e-05 0.02233466251575927 6.400548026010642e-05 7.851384429634715e-313 285120.47552 
0.0078125 33152 1.310388402561291e-06 9.089958496460984e-06 0.00273843177933682 3.756620668856767e-06 4.662248703783952e-310 570240.95104 
</Matrix>
 <string label="Label" id="1">Meshsize, dofs, l2err, h1err, h2err, iFaceErr, cond_num, (penalty)</string>
 <string label="Degree" id="2">4</string>
 <string label="Regularity" id="3">3</string>
 <string label="NumRefine" id="4">5</string>
 <string label="Method" id="5">3</string>
</xml>

