<?xml version="1.0" encoding="UTF-8"?>
<!--This file was created by G+Smo 21.12.0-->
<xml>
 <Matrix rows="6" cols="8" id="0">0.25 44 0.3558355489357488 6.302293623123715 117.7231701140017 1.121809250092863 1.144307396609573e-313 21.46988 
0.125 152 0.01556071504775694 0.461564319637454 16.26877557742697 0.1696286727150993 0 42.93976 
0.0625 560 0.0001274741752176139 0.01076320722198425 0.9733228942686621 0.002298672374402067 4.687083095736536e-310 85.87952 
0.03125 2144 2.538129221996081e-06 0.0004855015939379995 0.09519919509340119 9.45457660854657e-05 4.687083096124674e-310 171.75904 
0.015625 8384 6.939949651071196e-08 2.762826554044036e-05 0.0111321907213688 5.6157403008685e-06 9.973380220599987e-313 343.51808 
0.0078125 33152 2.056182204977123e-08 1.707975458591664e-06 0.001368529013927499 3.487092465896057e-07 0 687.03616 
</Matrix>
 <string label="Label" id="1">Meshsize, dofs, l2err, h1err, h2err, iFaceErr, cond_num, (penalty)</string>
 <string label="Degree" id="2">4</string>
 <string label="Regularity" id="3">3</string>
 <string label="NumRefine" id="4">5</string>
 <string label="Method" id="5">3</string>
</xml>

