<?xml version="1.0" encoding="UTF-8"?>
<!--This file was created by G+Smo 21.12.0-->
<xml>
 <Matrix rows="6" cols="8" id="0">0.25 27 0.5143461005588982 6.913357811399622 114.0428499710533 0.9916687189606017 1.134588760735429e-313 2691.02372 
0.125 119 0.09505487772329013 1.690864085269408 37.80691497227953 0.2689768141492653 0 5382.04744 
0.0625 495 0.003899183709856003 0.07970187624755362 4.434466386095785 0.05175271517064275 4.647275566282965e-310 10764.09488 
0.03125 2015 9.342446338064464e-05 0.003543262366227745 0.9360906100794236 0.005218439230429696 4.647275564735156e-310 21528.18976 
0.015625 8127 3.476689256828411e-06 0.0003758471655498456 0.2279556243086288 0.0006040041414278381 8.912382325117351e-313 43056.37952 
0.0078125 32639 1.611204865244339e-07 4.572960288643208e-05 0.05660069951743932 7.39912013164545e-05 2.12448227711736e-322 86112.75904 
</Matrix>
 <string label="Label" id="1">Meshsize, dofs, l2err, h1err, h2err, iFaceErr, cond_num, (penalty)</string>
 <string label="Degree" id="2">3</string>
 <string label="Regularity" id="3">2</string>
 <string label="NumRefine" id="4">5</string>
 <string label="Method" id="5">3</string>
</xml>

