<?xml version="1.0" encoding="UTF-8"?>
<!--This file was created by G+Smo 21.12.0-->
<xml>
 <Matrix rows="6" cols="8" id="0">0.25 44 0.1413457920652973 3.355845093231271 145.6605431682652 15.40098365570571 1.143305097837277e-313 32.67924 
0.125 152 0.004620704479694052 0.1527614043719102 7.69742658453573 0.392845824638369 0 65.35848 
0.0625 560 3.911915846122688e-05 0.004094826729948413 0.5598177932593882 0.01293217142308076 4.682977683052131e-310 130.71696 
0.03125 2144 7.395676763033574e-07 0.0001983796751023073 0.0582923187029689 0.0006542804170776372 4.682977681504322e-310 261.43392 
0.015625 8384 2.031318297309755e-08 1.159786322598204e-05 0.006976766622232814 4.697969608031998e-05 8.912382325117351e-313 522.86784 
0.0078125 33152 9.222928236009425e-10 7.403218970971556e-07 0.0009631643077736308 9.13596390496803e-06 2.12448227711736e-322 1045.73568 
</Matrix>
 <string label="Label" id="1">Meshsize, dofs, l2err, h1err, h2err, iFaceErr, cond_num, (penalty)</string>
 <string label="Degree" id="2">4</string>
 <string label="Regularity" id="3">3</string>
 <string label="NumRefine" id="4">5</string>
 <string label="Method" id="5">3</string>
</xml>

