<?xml version="1.0" encoding="UTF-8"?>
<!--This file was created by G+Smo 21.12.0-->
<xml>
 <Matrix rows="5" cols="9" id="0">0.25 73 0.02421125438038705 0.4665405319532544 18.10047773769982 0.1796690295392942 8.387793956833756e-4941 3290.048887639732 2228.618794875839 
0.125 241 0.0006003209278502274 0.01346822408906425 1.003042229917766 0.008629907395338663 0 5912.040206935187 4073.950217159058 
0.0625 865 3.556052590236969e-06 0.0003463949410574271 0.08808344281666351 0.0002002454864055587 nan 10665.80758176437 7873.124306131913 
0.03125 3265 9.309203225999702e-08 1.936653808002967e-05 0.01045246214539268 9.648577750387256e-06 nan 21331.61516352874 15746.24861226383 
0.015625 12673 3.543581410533461e-09 1.181507523667628e-06 0.001296240028969473 5.682813123319693e-07 nan 42663.23032705748 31492.49722452765 
</Matrix>
 <string label="Label" id="1">Meshsize, dofs, l2err, h1err, h2err, iFaceErr, cond_num, (penalty)</string>
 <string label="Degree" id="2">4</string>
 <string label="Regularity" id="3">3</string>
 <string label="NumRefine" id="4">4</string>
 <string label="Method" id="5">3</string>
</xml>

